Workbook

Sheet Supuestos
A1: Una Manito · Supuestos del modelo
A2: Celdas azules con fondo amarillo = puedes cambiarlas. Todo lo demás se recalcula solo.
A4: Concepto | B4: Valor | C4: Fuente / nota
A5: Generales
A6: Comisión a la socia | B6: 0.15 | C6: Configurada en la app (Admin → Ajustes).
A7: Cargo de servicio al cliente (S/ por orden) | B7: 0 | C7: Recomendación del estudio: S/3–5. Pon 4 para ver el escenario con cargo.
A8: IGV | B8: 0.18 | C8: SUNAT. La comisión se asume con IGV incluido.
A9: % de pagos por Yape/Plin (pasarela) | B9: 0.6 | C9: Supuesto propio.
A10: % de pagos con tarjeta | B10: 0.2 | C10: Supuesto propio. El resto se asume efectivo.
A11: Comisión pasarela Yape/Plin | B11: 0.015 | C11: Izipay 1.5% (kom.pe, 2026). Confirmar tarifario.
A12: Comisión pasarela tarjeta | B12: 0.042 | C12: Culqi hasta 4.2% (tarifario abril 2026).
A13: Cargo fijo por pago con tarjeta (S/) | B13: 0.3 | C13: Izipay/Culqi ~S/0.30.
A14: Soporte / incidencias por orden (S/) | B14: 0.4 | C14: Supuesto propio (atención, reembolsos).
A15: Crecimiento y clientes
A16: Órdenes en el mes 1 | B16: 150 | C16: Supuesto propio para el piloto.
A17: Crecimiento mensual de órdenes | B17: 0.2 | C17: Supuesto propio.
A18: Órdenes por cliente al mes | B18: 1.5 | C18: Cliente quincenal ≈ 2; ocasional ≈ 1.
A19: % de clientes que se van cada mes (churn) | B19: 0.25 | C19: Homejoy tenía ~75% de abandono al mes 1; meta piloto ≤ 60%.
A20: Costo de conseguir un cliente (CAC, S/) | B20: 25 | C20: Estudio: S/15–37 con anuncios en Meta/TikTok.
A21: Escenario de costos fijos (1=Mínimo, 2=Equipo pequeño, 3=Crecimiento) | B21: 1 | C21: Elige 1, 2 o 3.

Sheet Por orden
A1: Lo que deja cada orden, por servicio
A3: Concepto | B3: Limpieza | C3: Gasfitería | D3: Electricidad | E3: Lavado de autos | F3: Piscinas | G3: Promedio ponderado
A4: Precio por hora (S/) | B4: 15 | C4: 35 | D4: 35 | E4: 25 | F4: 30
A5: Horas por orden | B5: 3 | C5: 2 | D5: 2 | E5: 1 | F5: 2
A6: Materiales (S/) | B6: 10 | C6: 0 | D6: 0 | E6: 5 | F6: 15
A7: Mezcla de órdenes (%) | B7: 0.7 | C7: 0.1 | D7: 0.1 | E7: 0.05 | F7: 0.05 | G7: =SUM(B7:F7)
A8: Mano de obra (S/) | B8: =B4*B5 | C8: =C4*C5 | D8: =D4*D5 | E8: =E4*E5 | F8: =F4*F5 | G8: =SUMPRODUCT(B8:F8,$B$7:$F$7)
A9: Ticket que paga el cliente (S/) | B9: =B8+B6+Supuestos!$B$7 | C9: =C8+C6+Supuestos!$B$7 | D9: =D8+D6+Supuestos!$B$7 | E9: =E8+E6+Supuestos!$B$7 | F9: =F8+F6+Supuestos!$B$7 | G9: =SUMPRODUCT(B9:F9,$B$7:$F$7)
A10: Comisión de la plataforma (S/) | B10: =ROUND(B8*Supuestos!$B$6,2) | C10: =ROUND(C8*Supuestos!$B$6,2) | D10: =ROUND(D8*Supuestos!$B$6,2) | E10: =ROUND(E8*Supuestos!$B$6,2) | F10: =ROUND(F8*Supuestos!$B$6,2) | G10: =SUMPRODUCT(B10:F10,$B$7:$F$7)
A11: Cargo de servicio (S/) | B11: =Supuestos!$B$7 | C11: =Supuestos!$B$7 | D11: =Supuestos!$B$7 | E11: =Supuestos!$B$7 | F11: =Supuestos!$B$7 | G11: =SUMPRODUCT(B11:F11,$B$7:$F$7)
A12: Ingreso bruto plataforma (S/) | B12: =B10+B11 | C12: =C10+C11 | D12: =D10+D11 | E12: =E10+E11 | F12: =F10+F11 | G12: =SUMPRODUCT(B12:F12,$B$7:$F$7)
A13: Ingreso sin IGV (S/) | B13: =B12/(1+Supuestos!$B$8) | C13: =C12/(1+Supuestos!$B$8) | D13: =D12/(1+Supuestos!$B$8) | E13: =E12/(1+Supuestos!$B$8) | F13: =F12/(1+Supuestos!$B$8) | G13: =SUMPRODUCT(B13:F13,$B$7:$F$7)
A14: Costo pasarela (S/) | B14: =B9*(Supuestos!$B$9*Supuestos!$B$11+Supuestos!$B$10*Supuestos!$B$12)+Supuestos!$B$10*Supuestos!$B$13 | C14: =C9*(Supuestos!$B$9*Supuestos!$B$11+Supuestos!$B$10*Supuestos!$B$12)+Supuestos!$B$10*Supuestos!$B$13 | D14: =D9*(Supuestos!$B$9*Supuestos!$B$11+Supuestos!$B$10*Supuestos!$B$12)+Supuestos!$B$10*Supuestos!$B$13 | E14: =E9*(Supuestos!$B$9*Supuestos!$B$11+Supuestos!$B$10*Supuestos!$B$12)+Supuestos!$B$10*Supuestos!$B$13 | F14: =F9*(Supuestos!$B$9*Supuestos!$B$11+Supuestos!$B$10*Supuestos!$B$12)+Supuestos!$B$10*Supuestos!$B$13 | G14: =SUMPRODUCT(B14:F14,$B$7:$F$7)
A15: Soporte (S/) | B15: =Supuestos!$B$14 | C15: =Supuestos!$B$14 | D15: =Supuestos!$B$14 | E15: =Supuestos!$B$14 | F15: =Supuestos!$B$14 | G15: =SUMPRODUCT(B15:F15,$B$7:$F$7)
A16: Contribución por orden (S/) | B16: =B13-B14-B15 | C16: =C13-C14-C15 | D16: =D13-D14-D15 | E16: =E13-E14-E15 | F16: =F13-F14-F15 | G16: =SUMPRODUCT(B16:F16,$B$7:$F$7)
A17: Margen sobre ticket (%) | B17: =IFERROR(B16/B9,0) | C17: =IFERROR(C16/C9,0) | D17: =IFERROR(D16/D9,0) | E17: =IFERROR(E16/E9,0) | F17: =IFERROR(F16/F9,0) | G17: =IFERROR(G16/G9,0)
A18: Lo que recibe la socia (S/) | B18: =B8-B10+B6 | C18: =C8-C10+C6 | D18: =D8-D10+D6 | E18: =E8-E10+E6 | F18: =F8-F10+F6 | G18: =SUMPRODUCT(B18:F18,$B$7:$F$7)
A20: La mezcla debe sumar 100%. Precios de la app (src/lib/config.ts). Materiales pasan íntegros a la socia.

Sheet Costos fijos
A1: Costos fijos mensuales por escenario (S/)
A3: Partida | B3: 1. Mínimo | C3: 2. Equipo pequeño | D3: 3. Crecimiento | E3: Nota
A4: Sueldos fundadores | B4: 0 | C4: 0 | D4: 6000 | E4: Escenario 3 incluye sueldo.
A5: Operaciones / soporte | B5: 0 | C5: 1635 | D5: 3270 | E5: Sueldo mínimo S/1,130 + EsSalud; Computrabajo.
A6: Community manager | B6: 0 | C6: 3270 | D6: 3270 | E6: Coderhouse 2025: S/2.8–5.2k.
A7: Contador | B7: 500 | C7: 500 | D7: 800 | E7: Estimación.
A8: Software (Supabase, Vercel, dominio, correo) | B8: 200 | C8: 300 | D8: 600 | E8: Estimación; planes gratuitos al inicio.
A9: Marketing | B9: 1500 | C9: 3000 | D9: 6000 | E9: Anuncios + referidos.
A10: Seguros, legal y otros | B10: 300 | C10: 395 | D10: 60 | E10: Estimación.
A11: Total | B11: =SUM(B4:B10) | C11: =SUM(C4:C10) | D11: =SUM(D4:D10)
A13: Escenario elegido en Supuestos | B13: =INDEX(B11:D11,1,Supuestos!$B$21)

Sheet Punto de equilibrio
A1: ¿Cuántas órdenes al mes para no perder?
A3: Contribución promedio por orden (con el cargo de Supuestos) | B3: ='Por orden'!G16
A4: Contribución promedio sin cargo de servicio | B4: =SUMPRODUCT('Por orden'!B10:F10,'Por orden'!B7:F7)/(1+Supuestos!$B$8)-SUMPRODUCT('Por orden'!B8:F8+'Por orden'!B6:F6,'Por orden'!B7:F7)*(Supuestos!$B$9*Supuestos!$B$11+Supuestos!$B$10*Supuestos!$B$12)-Supuestos!$B$10*Supuestos!$B$13-Supuestos!$B$14
A5: Contribución promedio con cargo de S/4 | B5: =B4+4/(1+Supuestos!$B$8)-4*(Supuestos!$B$9*Supuestos!$B$11+Supuestos!$B$10*Supuestos!$B$12)
A7: Escenario | B7: Costos fijos/mes | C7: Órdenes (sin cargo) | D7: Órdenes (cargo S/4) | E7: Socias activas necesarias* | F7: Clientes quincenales necesarios
A8: 1. Mínimo | B8: ='Costos fijos'!B11 | C8: =IFERROR(ROUNDUP(B8/$B$4,0),0) | D8: =IFERROR(ROUNDUP(B8/$B$5,0),0) | E8: =ROUNDUP(C8/34,0) | F8: =ROUNDUP(C8/2,0)
A9: 2. Equipo pequeño | B9: ='Costos fijos'!C11 | C9: =IFERROR(ROUNDUP(B9/$B$4,0),0) | D9: =IFERROR(ROUNDUP(B9/$B$5,0),0) | E9: =ROUNDUP(C9/34,0) | F9: =ROUNDUP(C9/2,0)
A10: 3. Crecimiento | B10: ='Costos fijos'!D11 | C10: =IFERROR(ROUNDUP(B10/$B$4,0),0) | D10: =IFERROR(ROUNDUP(B10/$B$5,0),0) | E10: =ROUNDUP(C10/34,0) | F10: =ROUNDUP(C10/2,0)
A12: * Una socia activa hace ~34 limpiezas al mes (≈ 8 por semana). Supuesto propio.

Sheet Proyección 12 meses
A1: Proyección mensual (escenario elegido en Supuestos)
A3: Mes | B3: Órdenes | C3: Clientes activos | D3: Clientes nuevos | E3: Ingreso bruto (S/) | F3: Contribución (S/) | G3: Costo de adquisición (S/) | H3: Costos fijos (S/) | I3: Resultado del mes (S/) | J3: Resultado acumulado (S/) | K3: GMV — total pagado por clientes (S/) | L3: Pagado a socias (S/)
A4: Mes 1 | B4: =Supuestos!$B$16 | C4: =B4/Supuestos!$B$18 | D4: =C4 | E4: =B4*'Por orden'!$G$12 | F4: =B4*'Por orden'!$G$16 | G4: =D4*Supuestos!$B$20 | H4: ='Costos fijos'!$B$13 | I4: =F4-G4-H4 | J4: =I4 | K4: =B4*'Por orden'!$G$9 | L4: =B4*'Por orden'!$G$18
A5: Mes 2 | B5: =ROUND(B4*(1+Supuestos!$B$17),0) | C5: =B5/Supuestos!$B$18 | D5: =MAX(0,C5-C4*(1-Supuestos!$B$19)) | E5: =B5*'Por orden'!$G$12 | F5: =B5*'Por orden'!$G$16 | G5: =D5*Supuestos!$B$20 | H5: ='Costos fijos'!$B$13 | I5: =F5-G5-H5 | J5: =J4+I5 | K5: =B5*'Por orden'!$G$9 | L5: =B5*'Por orden'!$G$18
A6: Mes 3 | B6: =ROUND(B5*(1+Supuestos!$B$17),0) | C6: =B6/Supuestos!$B$18 | D6: =MAX(0,C6-C5*(1-Supuestos!$B$19)) | E6: =B6*'Por orden'!$G$12 | F6: =B6*'Por orden'!$G$16 | G6: =D6*Supuestos!$B$20 | H6: ='Costos fijos'!$B$13 | I6: =F6-G6-H6 | J6: =J5+I6 | K6: =B6*'Por orden'!$G$9 | L6: =B6*'Por orden'!$G$18
A7: Mes 4 | B7: =ROUND(B6*(1+Supuestos!$B$17),0) | C7: =B7/Supuestos!$B$18 | D7: =MAX(0,C7-C6*(1-Supuestos!$B$19)) | E7: =B7*'Por orden'!$G$12 | F7: =B7*'Por orden'!$G$16 | G7: =D7*Supuestos!$B$20 | H7: ='Costos fijos'!$B$13 | I7: =F7-G7-H7 | J7: =J6+I7 | K7: =B7*'Por orden'!$G$9 | L7: =B7*'Por orden'!$G$18
A8: Mes 5 | B8: =ROUND(B7*(1+Supuestos!$B$17),0) | C8: =B8/Supuestos!$B$18 | D8: =MAX(0,C8-C7*(1-Supuestos!$B$19)) | E8: =B8*'Por orden'!$G$12 | F8: =B8*'Por orden'!$G$16 | G8: =D8*Supuestos!$B$20 | H8: ='Costos fijos'!$B$13 | I8: =F8-G8-H8 | J8: =J7+I8 | K8: =B8*'Por orden'!$G$9 | L8: =B8*'Por orden'!$G$18
A9: Mes 6 | B9: =ROUND(B8*(1+Supuestos!$B$17),0) | C9: =B9/Supuestos!$B$18 | D9: =MAX(0,C9-C8*(1-Supuestos!$B$19)) | E9: =B9*'Por orden'!$G$12 | F9: =B9*'Por orden'!$G$16 | G9: =D9*Supuestos!$B$20 | H9: ='Costos fijos'!$B$13 | I9: =F9-G9-H9 | J9: =J8+I9 | K9: =B9*'Por orden'!$G$9 | L9: =B9*'Por orden'!$G$18
A10: Mes 7 | B10: =ROUND(B9*(1+Supuestos!$B$17),0) | C10: =B10/Supuestos!$B$18 | D10: =MAX(0,C10-C9*(1-Supuestos!$B$19)) | E10: =B10*'Por orden'!$G$12 | F10: =B10*'Por orden'!$G$16 | G10: =D10*Supuestos!$B$20 | H10: ='Costos fijos'!$B$13 | I10: =F10-G10-H10 | J10: =J9+I10 | K10: =B10*'Por orden'!$G$9 | L10: =B10*'Por orden'!$G$18
A11: Mes 8 | B11: =ROUND(B10*(1+Supuestos!$B$17),0) | C11: =B11/Supuestos!$B$18 | D11: =MAX(0,C11-C10*(1-Supuestos!$B$19)) | E11: =B11*'Por orden'!$G$12 | F11: =B11*'Por orden'!$G$16 | G11: =D11*Supuestos!$B$20 | H11: ='Costos fijos'!$B$13 | I11: =F11-G11-H11 | J11: =J10+I11 | K11: =B11*'Por orden'!$G$9 | L11: =B11*'Por orden'!$G$18
A12: Mes 9 | B12: =ROUND(B11*(1+Supuestos!$B$17),0) | C12: =B12/Supuestos!$B$18 | D12: =MAX(0,C12-C11*(1-Supuestos!$B$19)) | E12: =B12*'Por orden'!$G$12 | F12: =B12*'Por orden'!$G$16 | G12: =D12*Supuestos!$B$20 | H12: ='Costos fijos'!$B$13 | I12: =F12-G12-H12 | J12: =J11+I12 | K12: =B12*'Por orden'!$G$9 | L12: =B12*'Por orden'!$G$18
A13: Mes 10 | B13: =ROUND(B12*(1+Supuestos!$B$17),0) | C13: =B13/Supuestos!$B$18 | D13: =MAX(0,C13-C12*(1-Supuestos!$B$19)) | E13: =B13*'Por orden'!$G$12 | F13: =B13*'Por orden'!$G$16 | G13: =D13*Supuestos!$B$20 | H13: ='Costos fijos'!$B$13 | I13: =F13-G13-H13 | J13: =J12+I13 | K13: =B13*'Por orden'!$G$9 | L13: =B13*'Por orden'!$G$18
A14: Mes 11 | B14: =ROUND(B13*(1+Supuestos!$B$17),0) | C14: =B14/Supuestos!$B$18 | D14: =MAX(0,C14-C13*(1-Supuestos!$B$19)) | E14: =B14*'Por orden'!$G$12 | F14: =B14*'Por orden'!$G$16 | G14: =D14*Supuestos!$B$20 | H14: ='Costos fijos'!$B$13 | I14: =F14-G14-H14 | J14: =J13+I14 | K14: =B14*'Por orden'!$G$9 | L14: =B14*'Por orden'!$G$18
A15: Mes 12 | B15: =ROUND(B14*(1+Supuestos!$B$17),0) | C15: =B15/Supuestos!$B$18 | D15: =MAX(0,C15-C14*(1-Supuestos!$B$19)) | E15: =B15*'Por orden'!$G$12 | F15: =B15*'Por orden'!$G$16 | G15: =D15*Supuestos!$B$20 | H15: ='Costos fijos'!$B$13 | I15: =F15-G15-H15 | J15: =J14+I15 | K15: =B15*'Por orden'!$G$9 | L15: =B15*'Por orden'!$G$18
A16: Total año | B16: =SUM(B4:B15) | D16: =SUM(D4:D15) | E16: =SUM(E4:E15) | F16: =SUM(F4:F15) | G16: =SUM(G4:G15) | H16: =SUM(H4:H15) | I16: =SUM(I4:I15) | K16: =SUM(K4:K15) | L16: =SUM(L4:L15)
A18: Mes en que el resultado mensual pasa a positivo | E18: =IFERROR(INDEX(A4:A15,MATCH(TRUE,INDEX(I4:I15>0,0),0)),"Aún no en 12 meses")
A19: Inversión máxima necesaria (peor acumulado) | E19: =-MIN(0,MIN(J4:J15))

Sheet Ganancia socia
A1: Cuánto gana una socia de limpieza
A3: Limpiezas por semana | B3: 8
A4: Propina promedio por servicio (S/) | B4: 3
A5: Recibe por limpieza (sin materiales) | B5: ='Por orden'!B8-'Por orden'!B10+B4
A6: Por hora efectiva | B6: =B5/'Por orden'!B5
A7: Al mes (4.3 semanas) | B7: =B5*B3*4.3
A8: Comparación: sueldo mínimo 2026 | B8: 1130
A9: Comparación: agencia informal (~S/10/h) | B9: =10*'Por orden'!B5*B3*4.3
